[
  {
    "FECHA": "ENERO",
    "DOMINIO": "EEN-107",
    "MARCA": "CHEVROLET",
    "MODELO": "S-10",
    "COLOR": "GRIS",
    "N° DE MOTOR": 40704133385,
    "N° DE CHASIS": "9BG138AC03C423795",
    "COMISARIA": "18ø",
    "HORARIO": "TARDE",
    "Column10": "ROBO",
    "Column11": "VIGENTE"
  },
  {
    "FECHA": "ENERO",
    "DOMINIO": " AD146VW",
    "MARCA": "FIAT",
    "MODELO": "CRONOS",
    "COLOR": "GRIS",
    "N° DE MOTOR": 552805000000000,
    "N° DE CHASIS": "8AP359A49KU025495",
    "COMISARIA": "2ø",
    "HORARIO": "TARDE",
    "Column10": "",
    "Column11": "VIGENTE"
  },
  {
    "FECHA": "ENERO",
    "DOMINIO": "JLW-116",
    "MARCA": "WOLKSWAGEN",
    "MODELO": "AMAROK",
    "COLOR": "BLANCO",
    "N° DE MOTOR": "CDC014692",
    "N° DE CHASIS": "8AWDB42HXBA012703",
    "COMISARIA": "49§",
    "HORARIO": "",
    "Column10": "ROBO",
    "Column11": "VIGENTE"
  },
  {
    "FECHA": "ENERO",
    "DOMINIO": "MQL-546",
    "MARCA": "PEUGEOT",
    "MODELO": "308 SPORT",
    "COLOR": "",
    "N° DE MOTOR": "10FJBZ1789519",
    "N° DE CHASIS": "8ADA4C5FMJEG013417",
    "COMISARIA": "U.F.D.E",
    "HORARIO": "",
    "Column10": "EJEC. VARIA",
    "Column11": "VIGENTE"
  },
  {
    "FECHA": "ENERO",
    "DOMINIO": "PKL-821",
    "MARCA": "VOLKSWAGEN",
    "MODELO": "AMAROCK",
    "COLOR": "GRIS",
    "N° DE MOTOR": "CNE083845",
    "N° DE CHASIS": "8AWDB42H5GA020523",
    "COMISARIA": "21ø",
    "HORARIO": "",
    "Column10": "ROBO",
    "Column11": "VIGENTE"
  },
  {
    "FECHA": "ENERO",
    "DOMINIO": "AB376LU",
    "MARCA": "VOLKSWAGEN",
    "MODELO": "VOYAGE",
    "COLOR": "GRIS",
    "N° DE MOTOR": "CFZS09879",
    "N° DE CHASIS": "9BWDB45U0HT087705",
    "COMISARIA": "19§",
    "HORARIO": "NOCHE",
    "Column10": "HURTO",
    "Column11": "VIGENTE"
  },
  {
    "FECHA": "ENERO",
    "DOMINIO": "AF121RQ",
    "MARCA": "FIAT",
    "MODELO": "STRADA",
    "COLOR": "GRIS",
    "N° DE MOTOR": 552821000000000,
    "N° DE CHASIS": "9BD281D43NYW64632",
    "COMISARIA": "52ø",
    "HORARIO": "MA¥ANA",
    "Column10": "ROBO",
    "Column11": "VIGENTE"
  },
  {
    "FECHA": "ENERO",
    "DOMINIO": "NNQ-385",
    "MARCA": "CHEVROLET",
    "MODELO": "ONIX",
    "COLOR": "BLANCO",
    "N° DE MOTOR": "CGZ016616",
    "N° DE CHASIS": "9BGKS48T0EG174929",
    "COMISARIA": "1§",
    "HORARIO": "NOCHE",
    "Column10": "ROBO",
    "Column11": "VIGENTE"
  },
  {
    "FECHA": "ENERO",
    "DOMINIO": "JJO-485",
    "MARCA": "FIAT",
    "MODELO": "FIORINO",
    "COLOR": "BLANCO",
    "N° DE MOTOR": null,
    "N° DE CHASIS": "9BD25521AB8900338",
    "COMISARIA": "21ø",
    "HORARIO": "NOCHE",
    "Column10": "ROBO",
    "Column11": "VIGENTE"
  },
  {
    "FECHA": "ENERO",
    "DOMINIO": "A090BQO",
    "MARCA": "",
    "MODELO": "",
    "COLOR": "",
    "N° DE MOTOR": "",
    "N° DE CHASIS": "",
    "COMISARIA": "",
    "HORARIO": "",
    "Column10": "",
    "Column11": "VIGENTE"
  },
  {
    "FECHA": "ENERO",
    "DOMINIO": "AF121RU",
    "MARCA": "RENAULT",
    "MODELO": "STEPWAY",
    "COLOR": "GRIS",
    "N° DE MOTOR": "H4MJ759Q100220",
    "N° DE CHASIS": "8A15SRYEGNL153129",
    "COMISARIA": "7ø",
    "HORARIO": "TARDE",
    "Column10": "",
    "Column11": "VIGENTE"
  },
  {
    "FECHA": "ENERO",
    "DOMINIO": "AF849IF",
    "MARCA": "PEUGEOT",
    "MODELO": 208,
    "COLOR": "GRIS",
    "N° DE MOTOR": "10PRAQ0017463",
    "N° DE CHASIS": "8ADUWNFPVPG569759",
    "COMISARIA": "2ø",
    "HORARIO": "TARDE",
    "Column10": "",
    "Column11": "VIGENTE"
  },
  {
    "FECHA": "ENERO",
    "DOMINIO": "IBA-091",
    "MARCA": "NISSAN",
    "MODELO": "TEANA 350",
    "COLOR": "GRIS",
    "N° DE MOTOR": "VQ35316624C",
    "N° DE CHASIS": "JN1BAUJ329W000125",
    "COMISARIA": "2¦",
    "HORARIO": "",
    "Column10": "",
    "Column11": "VIGENTE"
  },
  {
    "FECHA": "ENERO",
    "DOMINIO": "IUB-104",
    "MARCA": "VOLKSWAGEN",
    "MODELO": "FOX 1.6",
    "COLOR": "NEGRO",
    "N° DE MOTOR": "CFZ747250",
    "N° DE CHASIS": "9BWAB45Z2A4127104",
    "COMISARIA": "4¦",
    "HORARIO": "TARDE",
    "Column10": "ROBO",
    "Column11": "VIGENTE"
  },
  {
    "FECHA": "FEBRERO",
    "DOMINIO": "MZV-435",
    "MARCA": "CHEVROLET",
    "MODELO": "SPIN",
    "COLOR": "VERDE OSCURO",
    "N° DE MOTOR": "BK4010849",
    "N° DE CHASIS": "9BGJB7560EB109225",
    "COMISARIA": "18°",
    "HORARIO": "",
    "Column10": "ROBO",
    "Column11": "VIGENTE"
  },
  {
    "FECHA": "ENERO",
    "DOMINIO": "EEN-107",
    "MARCA": "CHEVROLET",
    "MODELO": "S-10",
    "COLOR": "",
    "N° DE MOTOR": 40704133385,
    "N° DE CHASIS": "9BG138AC03C423795",
    "COMISARIA": "2°",
    "HORARIO": "",
    "Column10": "ROBO",
    "Column11": "VIGENTE"
  },
  {
    "FECHA": "ENERO",
    "DOMINIO": " AD146VW",
    "MARCA": "FIAT",
    "MODELO": "CRONOS",
    "COLOR": "",
    "N° DE MOTOR": 552804903270020,
    "N° DE CHASIS": "8AP359A49KU025495",
    "COMISARIA": "49º",
    "HORARIO": "",
    "Column10": "",
    "Column11": "VIGENTE"
  },
  {
    "FECHA": "ENERO",
    "DOMINIO": "JLW-116",
    "MARCA": "WOLKSWAGEN",
    "MODELO": "AMAROK",
    "COLOR": "",
    "N° DE MOTOR": "CDC014692",
    "N° DE CHASIS": "8AWDB42HXBA012703",
    "COMISARIA": "U.F.D.E",
    "HORARIO": "",
    "Column10": "ROBO",
    "Column11": "VIGENTE"
  },
  {
    "FECHA": "ENERO",
    "DOMINIO": "MQL-546",
    "MARCA": "PEUGEOT",
    "MODELO": "308 SPORT",
    "COLOR": "",
    "N° DE MOTOR": "10FJBZ1789519",
    "N° DE CHASIS": "8ADA4C5FMJEG013417",
    "COMISARIA": "21°",
    "HORARIO": "",
    "Column10": "EJEC. VARIA",
    "Column11": "VIGENTE"
  },
  {
    "FECHA": "ENERO",
    "DOMINIO": "PKL-821",
    "MARCA": "VOLKSWAGEN",
    "MODELO": "AMAROCK",
    "COLOR": "",
    "N° DE MOTOR": "CNE083845",
    "N° DE CHASIS": "8AWDB42H5GA020523",
    "COMISARIA": "19º",
    "HORARIO": "",
    "Column10": "ROBO",
    "Column11": "VIGENTE"
  },
  {
    "FECHA": "ENERO",
    "DOMINIO": "AB376LU",
    "MARCA": "VOLKSWAGEN",
    "MODELO": "VOYAGE",
    "COLOR": "",
    "N° DE MOTOR": "CFZS09879",
    "N° DE CHASIS": "9BWDB45U0HT087705",
    "COMISARIA": "52°",
    "HORARIO": "",
    "Column10": "HURTO",
    "Column11": "VIGENTE"
  },
  {
    "FECHA": "ENERO",
    "DOMINIO": "AF121RQ",
    "MARCA": "FIAT",
    "MODELO": "STRADA",
    "COLOR": "",
    "N° DE MOTOR": 552820597980872,
    "N° DE CHASIS": "9BD281D43NYW64632",
    "COMISARIA": "1º",
    "HORARIO": "",
    "Column10": "ROBO",
    "Column11": "VIGENTE"
  },
  {
    "FECHA": "ENERO",
    "DOMINIO": "NNQ-385",
    "MARCA": "CHEVROLET",
    "MODELO": "ONIX",
    "COLOR": "",
    "N° DE MOTOR": "CGZ016616",
    "N° DE CHASIS": "9BGKS48T0EG174929",
    "COMISARIA": "21°",
    "HORARIO": "",
    "Column10": "ROBO",
    "Column11": "VIGENTE"
  },
  {
    "FECHA": "ENERO",
    "DOMINIO": "JJO-485",
    "MARCA": "FIAT",
    "MODELO": "FIORINO",
    "COLOR": "",
    "N° DE MOTOR": null,
    "N° DE CHASIS": "9BD25521AB8900338",
    "COMISARIA": "",
    "HORARIO": "",
    "Column10": "ROBO",
    "Column11": "VIGENTE"
  },
  {
    "FECHA": "ENERO",
    "DOMINIO": "A090BQO",
    "MARCA": "",
    "MODELO": "",
    "COLOR": "",
    "N° DE MOTOR": "",
    "N° DE CHASIS": "",
    "COMISARIA": "7°",
    "HORARIO": "",
    "Column10": "",
    "Column11": "VIGENTE"
  },
  {
    "FECHA": "ENERO",
    "DOMINIO": "AF121RU",
    "MARCA": "RENAULT",
    "MODELO": "STEPWAY",
    "COLOR": "",
    "N° DE MOTOR": "H4MJ759Q100220",
    "N° DE CHASIS": "8A15SRYEGNL153129",
    "COMISARIA": "2°",
    "HORARIO": "",
    "Column10": "",
    "Column11": "VIGENTE"
  },
  {
    "FECHA": "ENERO",
    "DOMINIO": "AF849IF",
    "MARCA": "PEUGEOT",
    "MODELO": 208,
    "COLOR": "",
    "N° DE MOTOR": "10PRAQ0017463",
    "N° DE CHASIS": "8ADUWNFPVPG569759",
    "COMISARIA": "2ª",
    "HORARIO": "",
    "Column10": "",
    "Column11": "VIGENTE"
  },
  {
    "FECHA": "ENERO",
    "DOMINIO": "IBA-091",
    "MARCA": "NISSAN",
    "MODELO": "TEANA 350",
    "COLOR": "",
    "N° DE MOTOR": "VQ35316624C",
    "N° DE CHASIS": "JN1BAUJ329W000125",
    "COMISARIA": "4ª",
    "HORARIO": "",
    "Column10": "",
    "Column11": "VIGENTE"
  },
  {
    "FECHA": "ENERO",
    "DOMINIO": "IUB-104",
    "MARCA": "VOLKSWAGEN",
    "MODELO": "FOX 1.6",
    "COLOR": "",
    "N° DE MOTOR": "CFZ747250",
    "N° DE CHASIS": "9BWAB45Z2A4127104",
    "COMISARIA": "41º",
    "HORARIO": "",
    "Column10": "ROBO",
    "Column11": "VIGENTE"
  },
  {
    "FECHA": "FEBRERO",
    "DOMINIO": "MZV-435",
    "MARCA": "CHEVROLET",
    "MODELO": "SPIN",
    "COLOR": "",
    "N° DE MOTOR": "BK4010849",
    "N° DE CHASIS": "9BGJB7560EB109225",
    "COMISARIA": "1º",
    "HORARIO": "",
    "Column10": "ROBO",
    "Column11": "VIGENTE"
  },
  {
    "FECHA": "FEBRERO",
    "DOMINIO": "HZL-348",
    "MARCA": "MII",
    "MODELO": "COOPER S",
    "COLOR": "",
    "N° DE MOTOR": "B061I341N14B16AB",
    "N° DE CHASIS": "WMWMF71049TS27014",
    "COMISARIA": "46º",
    "HORARIO": "",
    "Column10": "ROBO",
    "Column11": "VIGENTE"
  },
  {
    "FECHA": "FEBRERO",
    "DOMINIO": "JRW-149",
    "MARCA": "RENAULT",
    "MODELO": "KANGOO",
    "COLOR": "",
    "N° DE MOTOR": "K9KA700D181062",
    "N° DE CHASIS": "8A1FCG715BL664575",
    "COMISARIA": "1º",
    "HORARIO": "",
    "Column10": "HURTO",
    "Column11": "VIGENTE"
  },
  {
    "FECHA": "FEBRERO",
    "DOMINIO": "NUO-553",
    "MARCA": "RENAULT",
    "MODELO": "CLIO",
    "COLOR": "",
    "N° DE MOTOR": "D4FG728Q181689",
    "N° DE CHASIS": "8A1BB2U01EL320006",
    "COMISARIA": "21º",
    "HORARIO": "",
    "Column10": "ROBO",
    "Column11": "VIGENTE"
  },
  {
    "FECHA": "FEBRERO",
    "DOMINIO": "IWQ-290",
    "MARCA": "CHEVROLET",
    "MODELO": "AGILE",
    "COLOR": "",
    "N° DE MOTOR": "U65008233",
    "N° DE CHASIS": "8AGCA4850BR105271",
    "COMISARIA": "F.D.E.",
    "HORARIO": "",
    "Column10": "",
    "Column11": "VIGENTE"
  },
  {
    "FECHA": "FEBRERO",
    "DOMINIO": "AG864OH",
    "MARCA": "TOYOTA",
    "MODELO": "SW 4",
    "COLOR": "",
    "N° DE MOTOR": "1GDJ010251",
    "N° DE CHASIS": "8AJBA3FS2S0372117",
    "COMISARIA": "DPTO DEL. ECON.",
    "HORARIO": "",
    "Column10": "TIRBACION POSESION",
    "Column11": "VIGENTE"
  },
  {
    "FECHA": "FEBRERO",
    "DOMINIO": "KKS-639",
    "MARCA": "VOLKSWAGEN",
    "MODELO": "PASSAT CC 2.0 TSI",
    "COLOR": "",
    "N° DE MOTOR": "CCZ155219",
    "N° DE CHASIS": "WVWBB63C7BE758435",
    "COMISARIA": "1º",
    "HORARIO": "",
    "Column10": "ESTAFA",
    "Column11": "VIGENTE"
  },
  {
    "FECHA": "FEBRERO",
    "DOMINIO": "AG644LS",
    "MARCA": "TOYOTA",
    "MODELO": "COROLLA CROSS",
    "COLOR": "",
    "N° DE MOTOR": "M20AAD68558",
    "N° DE CHASIS": "9BRK4AAGXS0142379",
    "COMISARIA": "1º",
    "HORARIO": "",
    "Column10": "ROBO CALIFICADO",
    "Column11": "VIGENTE"
  },
  {
    "FECHA": "FEBRERO",
    "DOMINIO": "AG644KR",
    "MARCA": "FIAT",
    "MODELO": "STRADA ULTRA T200 CVT",
    "COLOR": "",
    "N° DE MOTOR": 463564180585812,
    "N° DE CHASIS": "9BD281DMXRYF23728",
    "COMISARIA": "CRIA. 7º",
    "HORARIO": "",
    "Column10": "ROBO",
    "Column11": "VIGENTE"
  },
  {
    "FECHA": "FEBRERO",
    "DOMINIO": "AH418RP",
    "MARCA": "VOLKWAGEN",
    "MODELO": "AMAROK",
    "COLOR": "",
    "N° DE MOTOR": "CNE 141313",
    "N° DE CHASIS": "8AWJB62HXSA029774",
    "COMISARIA": "4º",
    "HORARIO": "",
    "Column10": "HURTO",
    "Column11": "VIGENTE"
  },
  {
    "FECHA": "FEBRERO",
    "DOMINIO": "OUC-005",
    "MARCA": "FIAT",
    "MODELO": "SIENA",
    "COLOR": "",
    "N° DE MOTOR": "178F40552679325",
    "N° DE CHASIS": "9BD197366F3219755",
    "COMISARIA": "5°",
    "HORARIO": "",
    "Column10": "",
    "Column11": "VIGENTE"
  },
  {
    "FECHA": "FEBRERO",
    "DOMINIO": "AE065QG",
    "MARCA": "TOYOTA",
    "MODELO": "RAV 4",
    "COLOR": "",
    "N° DE MOTOR": "A25AR216865",
    "N° DE CHASIS": "JTMY23FV3LD504797",
    "COMISARIA": "5°",
    "HORARIO": "",
    "Column10": "ROBO",
    "Column11": "VIGENTE"
  },
  {
    "FECHA": "FEBRERO",
    "DOMINIO": "AH519CX",
    "MARCA": "CITROEN",
    "MODELO": "BASALT",
    "COLOR": "",
    "N° DE MOTOR": 463556700965133,
    "N° DE CHASIS": "935CPFC67TB505034",
    "COMISARIA": "2º",
    "HORARIO": "",
    "Column10": "ROBO",
    "Column11": "VIGENTE"
  },
  {
    "FECHA": "FEBRERO",
    "DOMINIO": "AD626WV",
    "MARCA": "FIAT",
    "MODELO": "STRADA",
    "COLOR": "",
    "N° DE MOTOR": "178F40553323732",
    "N° DE CHASIS": "9BD578978KY257224",
    "COMISARIA": "20°",
    "HORARIO": "",
    "Column10": "HURTO",
    "Column11": "VIGENTE"
  },
  {
    "FECHA": "FEBRERO",
    "DOMINIO": "JEM-440",
    "MARCA": "CITROEN",
    "MODELO": "BERLINGO",
    "COLOR": "",
    "N° DE MOTOR": "10dg080011507",
    "N° DE CHASIS": "8BCGJN6ACBG518004",
    "COMISARIA": "2°",
    "HORARIO": "",
    "Column10": "HURTO",
    "Column11": "VIGENTE"
  },
  {
    "FECHA": "FEBRERO",
    "DOMINIO": "CHP-526",
    "MARCA": "DAEWO",
    "MODELO": "DAMAS VAN",
    "COLOR": "",
    "N° DE MOTOR": "F8CB600743",
    "N° DE CHASIS": "KLY7T11ZBVC033696",
    "COMISARIA": "14°",
    "HORARIO": "",
    "Column10": "ROBO",
    "Column11": "VIGENTE"
  },
  {
    "FECHA": "FEBRERO",
    "DOMINIO": "BXW-274",
    "MARCA": "MITSUBISHI",
    "MODELO": "L300",
    "COLOR": "",
    "N° DE MOTOR": "4D56JB3518",
    "N° DE CHASIS": "JMYJNP15VWA004853",
    "COMISARIA": "18º",
    "HORARIO": "",
    "Column10": "ROBO",
    "Column11": "VIGENTE"
  },
  {
    "FECHA": "FEBRERO",
    "DOMINIO": "ARX-471",
    "MARCA": "VOLKSWAGEN",
    "MODELO": "GOL GLI",
    "COLOR": "",
    "N° DE MOTOR": "UNC101855",
    "N° DE CHASIS": "8AWZZZ377TA801019",
    "COMISARIA": "41°",
    "HORARIO": "",
    "Column10": "ROBO",
    "Column11": "VIGENTE"
  },
  {
    "FECHA": "FEBRERO",
    "DOMINIO": "KSD-277",
    "MARCA": "CHEVROLET",
    "MODELO": "AVEO",
    "COLOR": "",
    "N° DE MOTOR": "F16D39163291",
    "N° DE CHASIS": "3G1TC5CF4BL154842",
    "COMISARIA": "1°",
    "HORARIO": "",
    "Column10": "ESTAFA",
    "Column11": "VIGENTE"
  },
  {
    "FECHA": "FEBRERO",
    "DOMINIO": "PDQ-058",
    "MARCA": "TOYOTA",
    "MODELO": "COROLLA",
    "COLOR": "",
    "N° DE MOTOR": "2ZRM326532",
    "N° DE CHASIS": "9BRBUWHE2G0040955",
    "COMISARIA": "3°",
    "HORARIO": "",
    "Column10": "",
    "Column11": "VIGENTE"
  },
  {
    "FECHA": "FEBRERO",
    "DOMINIO": "GRT-827",
    "MARCA": "FIAT",
    "MODELO": "PUNTO",
    "COLOR": "",
    "N° DE MOTOR": "J30324234",
    "N° DE CHASIS": "9BD11833781002551",
    "COMISARIA": "3°",
    "HORARIO": "",
    "Column10": "",
    "Column11": "VIGENTE"
  },
  {
    "FECHA": "MARZO",
    "DOMINIO": "PCJ682",
    "MARCA": "VOLKSWAGEN",
    "MODELO": "UP",
    "COLOR": "",
    "N° DE MOTOR": "CWR018521",
    "N° DE CHASIS": "9BWAG4124GT509899",
    "COMISARIA": "2°",
    "HORARIO": "",
    "Column10": "",
    "Column11": "VIGENTE"
  },
  {
    "FECHA": "MARZO",
    "DOMINIO": "DMR531",
    "MARCA": "VOLKSWAGEN",
    "MODELO": "POLO",
    "COLOR": "",
    "N° DE MOTOR": "1Y636773",
    "N° DE CHASIS": "8AWZZZ9EZYA522526",
    "COMISARIA": "",
    "HORARIO": "",
    "Column10": "",
    "Column11": "VIGENTE"
  },
  {
    "FECHA": "MARZO",
    "DOMINIO": "LUF507",
    "MARCA": "FORD",
    "MODELO": "RANGER2 DC 4X2 XL 2.5L N",
    "COLOR": "",
    "N° DE MOTOR": "EV2D CJ035967",
    "N° DE CHASIS": "8AFAR22D3CJ035967",
    "COMISARIA": "44º",
    "HORARIO": "",
    "Column10": "ESTAFA",
    "Column11": "VIGENTE"
  },
  {
    "FECHA": "MARZO",
    "DOMINIO": "KFZ-756",
    "MARCA": "CHEVROLET",
    "MODELO": "CLASSIC",
    "COLOR": "",
    "N° DE MOTOR": "T80017100",
    "N° DE CHASIS": "9BGSS1950BC241275",
    "COMISARIA": "1°",
    "HORARIO": "",
    "Column10": "ROBO CALIFICADO",
    "Column11": "VIGENTE"
  },
  {
    "FECHA": "MARZO",
    "DOMINIO": "EPD-381",
    "MARCA": "CHEVROLET",
    "MODELO": "CORA CALSSIC",
    "COLOR": "",
    "N° DE MOTOR": "7H5020997",
    "N° DE CHASIS": "8AGSB19N05R106582",
    "COMISARIA": "",
    "HORARIO": "",
    "Column10": "",
    "Column11": "VIGENTE"
  },
  {
    "FECHA": "febrero",
    "DOMINIO": "A279IVV",
    "MARCA": "HONDA",
    "MODELO": "WAVE 110",
    "COLOR": "",
    "N° DE MOTOR": "",
    "N° DE CHASIS": "",
    "COMISARIA": "",
    "HORARIO": "",
    "Column10": "",
    "Column11": "VIGENTE"
  },
  {
    "FECHA": "",
    "DOMINIO": "959KZY",
    "MARCA": "HONDA",
    "MODELO": "CG150TITAN",
    "COLOR": "",
    "N° DE MOTOR": "KC08E2E755203",
    "N° DE CHASIS": "8CHKC0830EP008803",
    "COMISARIA": "",
    "HORARIO": "",
    "Column10": "",
    "Column11": "VIGENTE"
  },
  {
    "FECHA": "",
    "DOMINIO": "A254YMY",
    "MARCA": "HONDA",
    "MODELO": "xr150",
    "COLOR": "",
    "N° DE MOTOR": "",
    "N° DE CHASIS": "",
    "COMISARIA": "",
    "HORARIO": "",
    "Column10": "",
    "Column11": "VIGENTE"
  },
  {
    "FECHA": "",
    "DOMINIO": "a261jag ",
    "MARCA": "HONDA",
    "MODELO": "XR190",
    "COLOR": "",
    "N° DE MOTOR": "",
    "N° DE CHASIS": "",
    "COMISARIA": "",
    "HORARIO": "",
    "Column10": "",
    "Column11": "VIGENTE"
  },
  {
    "FECHA": "",
    "DOMINIO": "",
    "MARCA": "",
    "MODELO": "XR ",
    "COLOR": "",
    "N° DE MOTOR": "KD07E2506723",
    "N° DE CHASIS": "",
    "COMISARIA": "",
    "HORARIO": "",
    "Column10": "",
    "Column11": "VIGENTE"
  },
  {
    "FECHA": "",
    "DOMINIO": "AO451BP",
    "MARCA": "YAMAHA",
    "MODELO": "T110",
    "COLOR": "",
    "N° DE MOTOR": "E3L6E-287695",
    "N° DE CHASIS": "8C6KE1970H0038175",
    "COMISARIA": "",
    "HORARIO": "",
    "Column10": "",
    "Column11": "VIGENTE"
  },
  {
    "FECHA": "",
    "DOMINIO": "A279JAY",
    "MARCA": "GILERA",
    "MODELO": "VOGE 300DS",
    "COLOR": "",
    "N° DE MOTOR": "LC178MN*184589Q4*",
    "N° DE CHASIS": "8CXG300DSSN003774",
    "COMISARIA": "",
    "HORARIO": "",
    "Column10": "",
    "Column11": "VIGENTE"
  },
  {
    "FECHA": "",
    "DOMINIO": "AG477VP",
    "MARCA": "PEUGEOT",
    "MODELO": 208,
    "COLOR": "",
    "N° DE MOTOR": "10PRAP0027616",
    "N° DE CHASIS": "8ADUWNFPARG569570",
    "COMISARIA": "",
    "HORARIO": "",
    "Column10": "",
    "Column11": "VIGENTE"
  },
  {
    "FECHA": "",
    "DOMINIO": "",
    "MARCA": "morini",
    "MODELO": "007-x-cape1200",
    "COLOR": "",
    "N° DE MOTOR": "mm2v107myls3900324",
    "N° DE CHASIS": "hl4pu3ab5tz000233",
    "COMISARIA": "",
    "HORARIO": "",
    "Column10": "",
    "Column11": "VIGENTE"
  },
  {
    "FECHA": "",
    "DOMINIO": "A277JZL",
    "MARCA": "HONDA",
    "MODELO": "WAVE 110",
    "COLOR": "",
    "N° DE MOTOR": "",
    "N° DE CHASIS": "",
    "COMISARIA": "",
    "HORARIO": "",
    "Column10": "",
    "Column11": "VIGENTE"
  }
]